utestcell/__init__.py
utestcell-0.0.15.dist-info/LICENSE
utestcell-0.0.15.dist-info/METADATA
utestcell-0.0.15.dist-info/WHEEL
utestcell-0.0.15.dist-info/top_level.txt
utestcell-0.0.15.dist-info/RECORD
