Metadata-Version: 2.1
Name: utestcell
Version: 0.0.15
Summary: Python magic to simplify unit testing in Colab and Jupyter
Home-page: https://github.com/pypa/sampleproject
Author: Remi Branco
Author-email: remi.branco@hotmail.fr
License: UNKNOWN
Project-URL: Bug Tracker, https://github.com/pypa/sampleproject/issues
Platform: UNKNOWN
Classifier: Programming Language :: Python :: 3
Classifier: License :: OSI Approved :: MIT License
Classifier: Operating System :: OS Independent
Classifier: Framework :: IPython
Requires-Python: >=3.6
License-File: LICENSE
